{"Football. FIFA Club World Cup.":[{"result":"1:2(0:1)","nameOne":"Esperanse de Tunis","nameTwo":"Al-Sadd","1":"2.30","X":"3.20","2":"3.10"}],"Football. England. Premier League.":[{"result":"1:0(0:0)","nameOne":"Arsenal London","nameTwo":"Everton","1":"1.52","X":"3.85","2":"5.85"},{"result":"1:2(0:2)","nameOne":"Bolton Wanderers","nameTwo":"Aston Villa","1":"2.40","X":"3.25","2":"2.85"},{"result":"1:0(0:0)","nameOne":"Liverpool","nameTwo":"Queens Park Rangers","1":"1.26","X":"5.10","2":"11.00"},{"result":"4:1(2:0)","nameOne":"Manchester United","nameTwo":"Wolverhampton Wanderers","1":"1.23","X":"5.50","2":"10.50"},{"result":"4:2(1:1)","nameOne":"Norwich City","nameTwo":"Newcastle United","1":"2.45","X":"3.30","2":"2.75"},{"result":"2:0(0:0)","nameOne":"Swansea City","nameTwo":"Fulham","1":"2.55","X":"3.20","2":"2.65"},{"result":"1:2(1:1)","nameOne":"West Bromwich Albion","nameTwo":"Wigan Athletic","1":"1.65","X":"3.55","2":"5.00"},{"result":"2:1(0:1)","nameOne":"Sunderland","nameTwo":"Blackburn Rovers","1":"1.85","X":"3.45","2":"4.00"},{"result":"2:1(2:0)","nameOne":"Stoke City","nameTwo":"Tottenham Hotspur","1":"3.60","X":"3.35","2":"1.95"},{"result":"2:1(1:1)","nameOne":"Chelsea","nameTwo":"Manchester City","1":"2.30","X":"3.30","2":"2.90"}],"Football. England. League Championship.":[{"result":"2:2(1:1)","nameOne":"Southampton","nameTwo":"Blackpool","1":"1.55","X":"3.70","2":"5.70"},{"result":"2:1(0:0)","nameOne":"Birmingham City","nameTwo":"Doncaster Rovers","1":"1.55","X":"3.70","2":"5.70"},{"result":"0:0(0:0)","nameOne":"Millwall","nameTwo":"Cardiff City","1":"2.50","X":"3.20","2":"2.60"},{"result":"0:1(0:0)","nameOne":"Coventry City","nameTwo":"Hull City","1":"2.60","X":"3.20","2":"2.50"},{"result":"0:1(0:0)","nameOne":"Burnley","nameTwo":"Portsmouth","1":"2.00","X":"3.30","2":"3.45"},{"result":"3:0(0:0)","nameOne":"Reading","nameTwo":"West Ham United","1":"2.50","X":"3.20","2":"2.60"},{"result":"1:1(1:0)","nameOne":"Watford","nameTwo":"Leeds United","1":"2.60","X":"3.20","2":"2.50"},{"result":"1:0(1:0)","nameOne":"Middlesbrough","nameTwo":"Brighton & Hove","1":"1.75","X":"3.50","2":"4.25"},{"result":"0:1(0:0)","nameOne":"Nottingham Forest","nameTwo":"Crystal Palace","1":"1.90","X":"3.35","2":"3.70"},{"result":"2:1(0:0)","nameOne":"Derby County","nameTwo":"Bristol City","1":"2.50","X":"3.20","2":"2.60"},{"result":"1:1(0:0)","nameOne":"Leicester City","nameTwo":"Peterborough United","1":"1.55","X":"3.70","2":"5.70"},{"result":"3:5(2:0)","nameOne":"Barnsley","nameTwo":"Ipswich Town","1":"2.00","X":"3.30","2":"3.45"}],"Football. England. League 1.":[{"result":"4:1(3:0)","nameOne":"Colchester United","nameTwo":"Bury FC","1":"1.95","X":"3.30","2":"3.60"},{"result":"0:1(0:1)","nameOne":"Huddersfield Town","nameTwo":"AFC Bournemouth","1":"1.55","X":"3.70","2":"5.70"},{"result":"3:2(1:1)","nameOne":"Wycombe Wanderers","nameTwo":"Chesterfield","1":"2.40","X":"3.25","2":"2.70"},{"result":"1:0(0:0)","nameOne":"Yeovil Town","nameTwo":"Notts County","1":"2.90","X":"3.30","2":"2.25"},{"result":"0:2(0:0)","nameOne":"Oldham Athletic","nameTwo":"Sheffield Wednesday","1":"2.50","X":"3.20","2":"2.60"},{"result":"0:0(0:0)","nameOne":"Preston North End","nameTwo":"Stevenage Borough","1":"2.45","X":"3.25","2":"2.65"},{"result":"3:0(0:0)","nameOne":"Leyton Orient","nameTwo":"Exeter City","1":"2.05","X":"3.30","2":"3.30"},{"result":"0:2(0:1)","nameOne":"Tranmere Rovers","nameTwo":"Milton Keynes Dons","1":"2.70","X":"3.25","2":"2.40"},{"result":"1:2(1:0)","nameOne":"Scunthorpe United","nameTwo":"Carlisle United","1":"2.50","X":"3.20","2":"2.60"},{"result":"1:1(1:1)","nameOne":"Walsall","nameTwo":"Charlton Athletic","1":"4.25","X":"3.50","2":"1.75"},{"result":"3:0(1:0)","nameOne":"Sheffield United","nameTwo":"Rochdale","1":"1.55","X":"3.70","2":"5.70"},{"result":"2:1(0:0)","nameOne":"Brentford","nameTwo":"Hartlepool United","1":"1.85","X":"3.40","2":"3.85"}],"Football. England. League 2.":[{"result":"1:0(0:0)","nameOne":"Torquay United","nameTwo":"Barnet FC","1":"1.85","X":"3.40","2":"3.85"},{"result":"0:2(0:2)","nameOne":"AFC Wimbledon","nameTwo":"Accrington Stanley","1":"2.30","X":"3.30","2":"2.80"},{"result":"1:1(0:0)","nameOne":"Bradford City","nameTwo":"Plymouth Argyle","1":"1.70","X":"3.55","2":"4.50"},{"result":"1:1(1:0)","nameOne":"Northampton Town","nameTwo":"Crewe Alexandra","1":"2.25","X":"3.30","2":"2.90"},{"result":"3:0(1:0)","nameOne":"Crawley Town","nameTwo":"Burton Albion","1":"1.47","X":"3.90","2":"6.50"}],"Football. Spain. Primera Division.":[{"result":"1:0(0:0)","nameOne":"Levante","nameTwo":"Sevilla","1":"2.85","X":"3.20","2":"2.50"},{"result":"2:1(0:0)","nameOne":"Real Betis","nameTwo":"Valencia","1":"3.10","X":"3.20","2":"2.35"},{"result":"1:3(1:1)","nameOne":"Real Madrid","nameTwo":"Barcelona","1":"2.40","X":"3.50","2":"2.85"},{"result":"1:3(0:2)","nameOne":"Rayo Vallecano","nameTwo":"Sporting Gijon","1":"2.05","X":"3.30","2":"3.60"},{"result":"1:0(0:0)","nameOne":"Getafe","nameTwo":"Granada","1":"1.72","X":"3.55","2":"5.00"},{"result":"1:1(0:0)","nameOne":"Villarreal","nameTwo":"Real Sociedad","1":"1.72","X":"3.60","2":"4.90"},{"result":"0:1(0:1)","nameOne":"Real Zaragoza","nameTwo":"Mallorca","1":"2.10","X":"3.20","2":"3.60"},{"result":"1:1(0:1)","nameOne":"Malaga","nameTwo":"Osasuna","1":"1.55","X":"3.90","2":"6.50"},{"result":"1:1(0:0)","nameOne":"Athletic Bilbao","nameTwo":"Racing Santander","1":"1.40","X":"4.50","2":"8.00"},{"result":"4:2(3:1)","nameOne":"Espanyol","nameTwo":"Atletico Madrid","1":"2.75","X":"3.30","2":"2.55"}],"Football. Spain. Segunda Division.":[{"result":"3:3(1:0)","nameOne":"Barcelona B","nameTwo":"Almeria","1":"1.75","X":"3.70","2":"4.40"},{"result":"0:0(0:0)","nameOne":"Sabadell","nameTwo":"Elche","1":"3.30","X":"3.10","2":"2.25"},{"result":"0:0(0:0)","nameOne":"Gimnastic de Tarragona","nameTwo":"Cordoba","1":"2.90","X":"3.05","2":"2.50"},{"result":"0:0(0:0)","nameOne":"AD Alcorcon","nameTwo":"Celta","1":"2.40","X":"3.10","2":"3.00"},{"result":"3:1(2:0)","nameOne":"Deportivo La Coruna","nameTwo":"Numancia","1":"1.57","X":"3.70","2":"6.20"},{"result":"0:0(0:0)","nameOne":"Cartagena FC","nameTwo":"Las Palmas","1":"2.30","X":"3.10","2":"3.20"},{"result":"1:1(0:0)","nameOne":"Recreativo","nameTwo":"Huesca","1":"1.90","X":"3.20","2":"4.30"},{"result":"2:2(0:2)","nameOne":"Hercules","nameTwo":"Real Valladolid","1":"2.25","X":"3.10","2":"3.30"}],"Football. Italy. Serie A.":[{"result":"2:3(1:1)","nameOne":"Lecce","nameTwo":"Lazio","1":"4.40","X":"3.15","2":"1.90"},{"result":"0:2(0:0)","nameOne":"Siena","nameTwo":"Genoa","1":"2.20","X":"3.05","2":"3.45"},{"result":"2:0(1:0)","nameOne":"Internazionale Milan","nameTwo":"Fiorentina","1":"1.85","X":"3.10","2":"4.75"},{"result":"0:1(0:0)","nameOne":"Palermo","nameTwo":"Cesena","1":"1.57","X":"3.55","2":"6.45"},{"result":"0:0(0:0)","nameOne":"Cagliari","nameTwo":"Parma","1":"2.10","X":"3.05","2":"3.75"},{"result":"1:1(0:1)","nameOne":"Atalanta","nameTwo":"Catania","1":"1.95","X":"3.10","2":"4.20"},{"result":"2:2(1:1)","nameOne":"Bologna","nameTwo":"AC Milan","1":"8.50","X":"4.00","2":"1.42"},{"result":"2:1(0:0)","nameOne":"Udinese","nameTwo":"Chievo","1":"1.42","X":"4.00","2":"8.50"},{"result":"1:1(0:0)","nameOne":"Novara","nameTwo":"Napoli","1":"4.25","X":"3.20","2":"1.90"},{"result":"1:1(1:0)","nameOne":"AS Roma","nameTwo":"Juventus","1":"4.05","X":"3.20","2":"1.95"}],"Football. Italy. Serie B.":[{"result":"1:1(0:0)","nameOne":"Sampdoria","nameTwo":"Juve Stabia","1":"1.60","X":"3.40","2":"6.10"},{"result":"0:0(0:0)","nameOne":"Ascoli Picchio","nameTwo":"Varese","1":"2.50","X":"2.90","2":"2.95"},{"result":"3:2(1:1)","nameOne":"Cittadella","nameTwo":"Reggina","1":"2.80","X":"2.90","2":"2.60"},{"result":"1:1(0:0)","nameOne":"Grosseto","nameTwo":"Modena","1":"1.90","X":"3.10","2":"4.25"},{"result":"1:0(1:0)","nameOne":"AS Gubbio 1910","nameTwo":"Padova","1":"3.80","X":"3.10","2":"2.00"},{"result":"0:2(0:0)","nameOne":"Nocerina","nameTwo":"Crotone","1":"2.05","X":"3.05","2":"3.75"},{"result":"2:1(0:1)","nameOne":"Sassuolo","nameTwo":"Livorno","1":"2.05","X":"2.95","2":"3.85"},{"result":"4:2(1:0)","nameOne":"Torino","nameTwo":"Pescara","1":"1.95","X":"3.40","2":"3.60"},{"result":"1:0(0:0)","nameOne":"Hellas Verona","nameTwo":"U.C. AlbinoLeffe","1":"1.67","X":"3.35","2":"5.30"},{"result":"1:0(0:0)","nameOne":"Vicenza","nameTwo":"Empoli","1":"2.25","X":"2.90","2":"3.40"},{"result":"1:3(1:1)","nameOne":"Brescia","nameTwo":"Bari","1":"2.00","X":"2.95","2":"4.05"}],"Football. Germany. Bundesliga.":[{"result":"1:2(1:2)","nameOne":"Hertha","nameTwo":"Schalke 04","1":"2.95","X":"3.50","2":"2.30"},{"result":"4:1(2:0)","nameOne":"Werder Bremen","nameTwo":"Wolfsburg","1":"1.58","X":"4.15","2":"5.20"},{"result":"0:0(0:0)","nameOne":"Mainz 05","nameTwo":"Hamburg","1":"2.20","X":"3.35","2":"3.15"},{"result":"0:2(0:1)","nameOne":"Nuremberg","nameTwo":"Hoffenheim","1":"2.25","X":"3.25","2":"3.15"},{"result":"4:0(1:0)","nameOne":"Cologne","nameTwo":"Freiburg","1":"2.25","X":"3.50","2":"2.95"},{"result":"1:0(0:0)","nameOne":"FC Augsburg","nameTwo":"Borussia Monchengladbach","1":"4.00","X":"3.55","2":"1.87"},{"result":"0:0(0:0)","nameOne":"Hannover 96","nameTwo":"Bayer Leverkusen","1":"2.75","X":"3.35","2":"2.45"},{"result":"1:1(1:0)","nameOne":"Borussia Dortmund","nameTwo":"Kaiserslautern","1":"1.22","X":"6.00","2":"12.00"},{"result":"1:2(1:1)","nameOne":"Stuttgart","nameTwo":"Bayern Munich","1":"5.65","X":"4.50","2":"1.50"},{"result":"12:8(6:4)","nameOne":"Home Germany 1","nameTwo":"Away Teams Germany 1","1":"","X":"","2":"14.512.5"}],"Football. Germany. 2 Bundesliga.":[{"result":"2:0(1:0)","nameOne":"Paderborn 07","nameTwo":"Hansa Rostock","1":"1.65","X":"3.55","2":"5.50"},{"result":"3:0(1:0)","nameOne":"1860 Munich","nameTwo":"Eintracht Braunschweig","1":"2.30","X":"3.40","2":"2.95"},{"result":"3:1(1:0)","nameOne":"MSV Duisburg","nameTwo":"Karlsruher","1":"1.68","X":"3.80","2":"4.75"},{"result":"1:1(1:0)","nameOne":"Bochum","nameTwo":"Fortuna Dusseldorf","1":"3.20","X":"3.30","2":"2.20"},{"result":"4:0(2:0)","nameOne":"Union Berlin","nameTwo":"Frankfurt","1":"1.65","X":"3.80","2":"5.00"},{"result":"1:1(0:0)","nameOne":"Alemannia Aachen","nameTwo":"Erzgebirge Aue","1":"1.82","X":"3.50","2":"4.25"},{"result":"1:0(0:0)","nameOne":"Ingolstadt 04","nameTwo":"St. Pauli","1":"3.80","X":"3.60","2":"1.90"},{"result":"2:1(0:0)","nameOne":"Dynamo Dresden","nameTwo":"Energie Cottbus","1":"2.20","X":"3.30","2":"3.20"},{"result":"0:0(0:0)","nameOne":"Eintracht Frankfurt","nameTwo":"Greuther Furth","1":"1.83","X":"3.65","2":"4.00"}],"Football. Germany. 3 Bundesliga.":[{"result":"1:1(0:0)","nameOne":"SV Wehen Wiesbaden","nameTwo":"Stuttgart II","1":"1.85","X":"3.40","2":"3.80"},{"result":"3:2(1:1)","nameOne":"Jahn Regensburg","nameTwo":"Werder Bremen II","1":"1.50","X":"3.80","2":"6.00"},{"result":"2:3(1:1)","nameOne":"Rot-Weiss Erfurt","nameTwo":"SV Babelsberg 03","1":"1.72","X":"3.40","2":"4.50"},{"result":"4:2(1:0)","nameOne":"SV Wacker Burghausen","nameTwo":"Carl Zeiss Jena","1":"1.72","X":"3.50","2":"4.35"},{"result":"5:2(1:1)","nameOne":"Saarbrucken","nameTwo":"Rot-Weiss Oberhausen","1":"1.50","X":"3.80","2":"6.00"},{"result":"3:1(1:0)","nameOne":"Heidenheim 1846","nameTwo":"Unterhaching","1":"1.80","X":"3.40","2":"4.00"},{"result":"2:2(1:0)","nameOne":"Prussia Munster","nameTwo":"Chemnitzer FC","1":"1.85","X":"3.40","2":"3.80"}],"Football. France. Ligue 1.":[{"result":"2:2(1:1)","nameOne":"Nancy","nameTwo":"AC Ajaccio","1":"1.70","X":"3.40","2":"5.30"},{"result":"1:1(1:1)","nameOne":"Rennes","nameTwo":"Stade Brestois 29","1":"1.60","X":"3.55","2":"6.10"},{"result":"2:0(1:0)","nameOne":"Saint-Etienne","nameTwo":"Caen","1":"1.85","X":"3.15","2":"4.65"},{"result":"0:1(0:1)","nameOne":"Sochaux-Montbeliard","nameTwo":"PSG","1":"4.50","X":"3.20","2":"1.85"},{"result":"2:1(1:0)","nameOne":"Toulouse","nameTwo":"Evian TG","1":"1.70","X":"3.35","2":"5.55"},{"result":"1:0(0:0)","nameOne":"Valenciennes FC","nameTwo":"Montpellier","1":"2.60","X":"2.90","2":"2.90"},{"result":"0:0(0:0)","nameOne":"Marseille","nameTwo":"Bordeaux","1":"1.70","X":"3.40","2":"5.30"},{"result":"2:1(1:1)","nameOne":"Auxerre","nameTwo":"Nice","1":"1.90","X":"3.05","2":"4.55"},{"result":"2:0(1:0)","nameOne":"Lille","nameTwo":"Dijon FCO","1":"1.25","X":"5.25","2":"12.00"},{"result":"0:1(0:0)","nameOne":"Lorient","nameTwo":"Lyon","1":"3.10","X":"3.00","2":"2.40"}],"Football. Ukraine. Premier League.":[{"result":"1:3(1:3)","nameOne":"Obolon","nameTwo":"Tavriya","1":"4.40","X":"3.45","2":"1.75"},{"result":"1:3(1:1)","nameOne":"FC Oleksandria","nameTwo":"Metalist Kharkiv","1":"9.00","X":"4.35","2":"1.35"},{"result":"0:1(0:0)","nameOne":"Karpaty Lviv","nameTwo":"Dynamo Kyiv","1":"7.75","X":"4.30","2":"1.38"},{"result":"1:0(1:0)","nameOne":"Dnipro","nameTwo":"Chornomorets Odesa","1":"1.35","X":"4.25","2":"9.00"},{"result":"2:0(2:0)","nameOne":"Arsenal Kyiv","nameTwo":"Vorskla Poltava","1":"2.05","X":"3.30","2":"3.40"},{"result":"3:0(2:0)","nameOne":"Metalurg Donetsk","nameTwo":"Zorya Luhansk","1":"1.45","X":"4.00","2":"6.75"},{"result":"0:1(0:1)","nameOne":"Volyn","nameTwo":"Illichivets Mariupol","1":"2.05","X":"3.30","2":"3.40"},{"result":"0:4(0:1)","nameOne":"Kryvbas","nameTwo":"Shakhtar Donetsk","1":"9.25","X":"4.90","2":"1.30"}],"Football. Ukraine. Youth championship":[{"result":"3:2(3:0)","nameOne":"Dnipro (res.)","nameTwo":"Chornomorets Odesa (res.)","1":"1.35","X":"4.50","2":"7.75"},{"result":"2:2(2:1)","nameOne":"Karpaty (res.)","nameTwo":"Dynamo Kyiv (res.)","1":"2.15","X":"3.45","2":"2.95"},{"result":"2:4(1:2)","nameOne":"Arsenal Kyiv (res.)","nameTwo":"Vorskla (res.)","1":"3.05","X":"3.45","2":"2.10"}],"Football. Belgium. Jupiler Pro League.":[{"result":"2:1(1:0)","nameOne":"Mechelen","nameTwo":"RSC Anderlecht","1":"6.40","X":"3.80","2":"1.47"},{"result":"1:1(0:0)","nameOne":"Lokeren","nameTwo":"Standard","1":"3.05","X":"3.25","2":"2.15"},{"result":"4:0(1:0)","nameOne":"KRC Genk","nameTwo":"Lierse","1":"1.37","X":"4.20","2":"7.60"},{"result":"0:1(0:0)","nameOne":"KAA Gent","nameTwo":"Beerschot Antwerp","1":"1.30","X":"4.55","2":"9.00"},{"result":"2:2(0:0)","nameOne":"Oud-Heverlee Leuven","nameTwo":"Zulte-Waregem","1":"2.85","X":"3.20","2":"2.30"},{"result":"1:0(0:0)","nameOne":"KV Kortrijk","nameTwo":"KVC Westerlo","1":"1.62","X":"3.50","2":"5.00"},{"result":"0:2(0:1)","nameOne":"RAEC Mons","nameTwo":"Cercle Brugge","1":"2.00","X":"3.25","2":"3.40"},{"result":"1:0(0:0)","nameOne":"Club Brugge KV","nameTwo":"Sint-Truiden","1":"1.25","X":"5.00","2":"10.00"}],"Football. Portugal. Liga Sagres.":[{"result":"5:2(2:1)","nameOne":"Sporting Braga","nameTwo":"Pacos de Ferreira","1":"1.30","X":"4.70","2":"9.00"}],"Football. Austria. Bundesliga.":[{"result":"0:0(0:0)","nameOne":"Rapid Wien","nameTwo":"FC Wacker Innsbruck","1":"1.50","X":"3.65","2":"6.20"},{"result":"2:0(2:0)","nameOne":"Mattersburg","nameTwo":"Kapfenberger SV","1":"1.67","X":"3.45","2":"4.75"},{"result":"2:0(1:0)","nameOne":"Ried","nameTwo":"Wiener Neustadt","1":"1.50","X":"3.60","2":"6.40"},{"result":"2:1(2:1)","nameOne":"FC Red Bull Salzburg","nameTwo":"FC Admira Wacker","1":"1.52","X":"3.65","2":"5.80"}],"Football. Holland. Eredivisie.":[{"result":"2:0(1:0)","nameOne":"ADO Den Haag","nameTwo":"Heracles Almelo","1":"2.50","X":"3.25","2":"2.40"},{"result":"2:0(0:0)","nameOne":"Twente","nameTwo":"NEC Nijmegen","1":"1.11","X":"6.10","2":"16.70"},{"result":"0:5(0:3)","nameOne":"Excelsior Rotterdam","nameTwo":"Heerenveen","1":"6.20","X":"4.10","2":"1.39"},{"result":"4:0(2:0)","nameOne":"AZ Alkmaar","nameTwo":"BV De Graafschap","1":"1.10","X":"6.05","2":"20.60"},{"result":"1:0(1:0)","nameOne":"PSV Eindhoven","nameTwo":"NAC Breda","1":"1.09","X":"6.60","2":"18.30"},{"result":"2:0(1:0)","nameOne":"VVV-Venlo","nameTwo":"Roda JC","1":"4.00","X":"3.30","2":"1.75"},{"result":"2:2(1:1)","nameOne":"Utrecht","nameTwo":"Feyenoord","1":"2.95","X":"3.25","2":"2.10"},{"result":"0:1(0:1)","nameOne":"RKC Waalwijk","nameTwo":"Ajax","1":"7.90","X":"4.40","2":"1.30"},{"result":"0:0(0:0)","nameOne":"SBV Vitesse","nameTwo":"FC Groningen","1":"1.95","X":"3.30","2":"3.25"}],"Football. Holland. Eerste Divisie.":[{"result":"3:1(1:0)","nameOne":"FC Oss","nameTwo":"Telstar","1":"2.30","X":"3.25","2":"2.60"},{"result":"3:1(0:0)","nameOne":"Fortuna Sittard","nameTwo":"Willem II","1":"4.00","X":"3.30","2":"1.75"},{"result":"1:2(1:1)","nameOne":"Emmen","nameTwo":"PEC Zwolle","1":"6.75","X":"4.40","2":"1.34"},{"result":"3:1(2:1)","nameOne":"FC Volendam","nameTwo":"Helmond Sport","1":"1.47","X":"4.20","2":"4.90"},{"result":"0:0(0:0)","nameOne":"Sparta Rotterdam","nameTwo":"MVV Maastricht","1":"1.37","X":"4.40","2":"6.10"},{"result":"2:2(1:0)","nameOne":"Go Ahead Eagles","nameTwo":"Almere City FC","1":"1.37","X":"4.40","2":"6.10"},{"result":"2:2(1:1)","nameOne":"FC Eindhoven","nameTwo":"FC Den Bosch","1":"2.30","X":"3.25","2":"2.60"},{"result":"5:1(3:1)","nameOne":"Cambuur Leeuwarden","nameTwo":"SC Veendam","1":"1.36","X":"4.50","2":"6.00"},{"result":"2:3(1:1)","nameOne":"AGOVV Apeldoorn","nameTwo":"FC Dordrecht","1":"4.40","X":"3.70","2":"1.60"}],"Football. Scotland. Premier League.":[{"result":"0:2(0:0)","nameOne":"Hibernian","nameTwo":"Rangers FC","1":"7.60","X":"4.10","2":"1.38"},{"result":"2:2(2:1)","nameOne":"Aberdeen F.C.","nameTwo":"Saint Mirren","1":"2.05","X":"3.20","2":"3.35"},{"result":"1:0(0:0)","nameOne":"Celtic","nameTwo":"Hearts","1":"1.28","X":"4.80","2":"9.10"},{"result":"2:3(1:0)","nameOne":"Inverness CT","nameTwo":"Dundee United","1":"2.65","X":"3.26","2":"2.40"},{"result":"0:3(0:2)","nameOne":"Saint Johnstone","nameTwo":"Motherwell","1":"2.45","X":"3.15","2":"2.70"}],"Football. Switzerland. Super League.":[{"result":"1:1(1:0)","nameOne":"FC Zurich","nameTwo":"FC Sion","1":"2.00","X":"3.25","2":"3.15"},{"result":"1:1(1:1)","nameOne":"FC Thun","nameTwo":"BSC Young Boys","1":"2.85","X":"3.25","2":"2.15"},{"result":"1:2(1:1)","nameOne":"FC Luzern","nameTwo":"Servette","1":"1.47","X":"3.80","2":"5.50"}],"Football. Wales. Premier League.":[{"result":"2:1(1:1)","nameOne":"Bangor City","nameTwo":"Bala Town FC","1":"1.55","X":"3.80","2":"5.20"},{"result":"3:2(1:1)","nameOne":"Afan Lido FC","nameTwo":"Newtown","1":"1.95","X":"3.40","2":"3.40"},{"result":"3:1(0:1)","nameOne":"Airbus UK Broughton","nameTwo":"Carmarthen Town","1":"1.50","X":"4.00","2":"5.40"}],"Football. Northern Ireland. IFA Premiership.":[{"result":"1:2(0:1)","nameOne":"Carrick Rangers","nameTwo":"Donegal Celtic","1":"2.75","X":"3.30","2":"2.30"},{"result":"3:1(1:0)","nameOne":"Cliftonville","nameTwo":"Lisburn Distillery","1":"1.35","X":"4.40","2":"7.50"},{"result":"3:2(3:1)","nameOne":"Coleraine","nameTwo":"Dungannon Swifts","1":"1.55","X":"3.80","2":"5.20"}],"Football. Australia. A-League.":[{"result":"1:2(0:2)","nameOne":"Brisbane Roar","nameTwo":"Melbourne Heart","1":"1.45","X":"3.85","2":"6.70"},{"result":"1:0(0:0)","nameOne":"Wellington Phoenix FC","nameTwo":"Perth Glory","1":"2.00","X":"3.20","2":"3.50"},{"result":"2:0(1:0)","nameOne":"Central Coast Mariners","nameTwo":"Newcastle Jets","1":"1.67","X":"3.50","2":"4.65"},{"result":"1:1(0:0)","nameOne":"Melbourne Victory","nameTwo":"Adelaide United","1":"1.70","X":"3.50","2":"4.50"}]}