{"Football. National teams. Asian Cup.":[{"result":"1:1(0:1)","nameOne":"Japan","nameTwo":"Jordan","1":"1.25","X":"5.20","2":"13.00"},{"result":"1:2(0:1)","nameOne":"Saudi Arabia","nameTwo":"Syria","1":"1.62","X":"3.65","2":"5.70"}],"Football. Youth national teams.":[{"result":"1:3(1:0), pass 2","nameOne":"Russia U-18","nameTwo":"Ukraine U-18","1":"1.55","X":"3.70","2":"5.15"},{"result":"2:0(0:0), pass 1","nameOne":"Finland U-18","nameTwo":"China PR U-18","1":"2.75","X":"3.05","2":"2.40"}],"Football. Clubs. Friendly matches.":[{"result":"4:0(2:0)","nameOne":"Union Berlin","nameTwo":"Teplice","1":"1.70","X":"3.30","2":"4.55"},{"result":"3:2(2:2)","nameOne":"Rot-Weiss Erfurt","nameTwo":"1860 Munich","1":"2.65","X":"3.25","2":"2.35"},{"result":"0:4(0:1)","nameOne":"FC Basel 1893","nameTwo":"Borussia Dortmund","1":"3.15","X":"3.25","2":"2.05"},{"result":"0:0(0:0)","nameOne":"MKE Ankaragucu","nameTwo":"Bochum","1":"2.60","X":"3.25","2":"2.40"},{"result":"cancelled","nameOne":"Fortuna Dusseldorf","nameTwo":"St. Pauli","1":"2.50","X":"3.25","2":"2.50"},{"result":"0:3(0:1)","nameOne":"Kardemir DC Karabukspor","nameTwo":"Schalke 04","1":"4.55","X":"3.30","2":"1.70"},{"result":"0:3(0:1)","nameOne":"Osnabruck","nameTwo":"Bayer Leverkusen","1":"6.15","X":"3.55","2":"1.50"},{"result":"cancelled","nameOne":"Borussia Monchengladbach","nameTwo":"Kaiserslautern","1":"2.60","X":"3.25","2":"2.40"},{"result":"1:1(0:0)","nameOne":"Hoffenheim","nameTwo":"Twente","1":"2.30","X":"3.25","2":"2.70"}],"Football. England. FA Cup.":[{"result":"1:0(1:0), pass 1","nameOne":"Manchester United","nameTwo":"Liverpool","1":"1.75","X":"3.50","2":"4.50"},{"result":"3:0(0:0), pass 1","nameOne":"Tottenham Hotspur","nameTwo":"Charlton Athletic","1":"1.26","X":"5.10","2":"11.00"},{"result":"7:0(3:0), pass 1","nameOne":"Chelsea","nameTwo":"Ipswich Town","1":"1.18","X":"6.25","2":"13.00"},{"result":"2:2(1:2), pass 2","nameOne":"Leicester City","nameTwo":"Manchester City","1":"4.50","X":"3.40","2":"1.75"},{"result":"2:1(1:0), pass 1","nameOne":"Crawley Town","nameTwo":"Derby County","1":"3.30","X":"3.25","2":"2.10"}],"Football. Spain. Primera Division.":[{"result":"4:1(2:0)","nameOne":"Mallorca","nameTwo":"Almeria","1":"1.70","X":"3.70","2":"5.00"},{"result":"0:0(0:0)","nameOne":"Osasuna","nameTwo":"Getafe","1":"2.15","X":"3.30","2":"3.50"},{"result":"4:0(3:0)","nameOne":"Espanyol","nameTwo":"Real Zaragoza","1":"1.80","X":"3.50","2":"4.60"},{"result":"1:1(1:0)","nameOne":"Racing Santander","nameTwo":"Sporting Gijon","1":"2.25","X":"3.20","2":"3.40"},{"result":"4:2(2:2)","nameOne":"Real Madrid","nameTwo":"Villarreal","1":"1.35","X":"5.50","2":"8.00"},{"result":"0:1(0:0)","nameOne":"Levante","nameTwo":"Valencia","1":"4.30","X":"3.55","2":"1.85"},{"result":"4:1(4:0)","nameOne":"Hercules","nameTwo":"Atletico Madrid","1":"2.90","X":"3.35","2":"2.40"}],"Football. Spain. Segunda Division.":[{"result":"0:1(0:0)","nameOne":"Xerez","nameTwo":"Rayo Vallecano","1":"2.25","X":"3.20","2":"3.10"},{"result":"1:1(0:0)","nameOne":"Huesca","nameTwo":"Real Betis","1":"3.80","X":"3.25","2":"1.95"},{"result":"0:1(0:1)","nameOne":"Tenerife","nameTwo":"Albacete Balompie, S.A.D.","1":"1.80","X":"3.30","2":"4.50"}],"Football. Italy. Serie A.":[{"result":"2:1(0:1)","nameOne":"Sampdoria","nameTwo":"AS Roma","1":"3.05","X":"3.05","2":"2.40"},{"result":"0:2(0:1)","nameOne":"Bari","nameTwo":"Bologna","1":"2.15","X":"3.05","2":"3.55"},{"result":"1:2(0:0)","nameOne":"Catania","nameTwo":"Internazionale Milan","1":"4.90","X":"3.20","2":"1.80"},{"result":"0:0(0:0)","nameOne":"Cesena","nameTwo":"Genoa","1":"3.10","X":"2.90","2":"2.45"},{"result":"0:0(0:0)","nameOne":"Chievo","nameTwo":"Palermo","1":"2.70","X":"3.00","2":"2.70"},{"result":"3:2(0:2)","nameOne":"Fiorentina","nameTwo":"Brescia","1":"1.55","X":"3.65","2":"6.45"},{"result":"1:2(0:1)","nameOne":"Lazio","nameTwo":"Lecce","1":"1.30","X":"4.90","2":"10.00"},{"result":"4:4(1:1)","nameOne":"AC Milan","nameTwo":"Udinese","1":"1.55","X":"3.65","2":"6.30"},{"result":"1:2(0:2)","nameOne":"Parma","nameTwo":"Cagliari","1":"1.85","X":"3.10","2":"4.75"},{"result":"3:0(2:0)","nameOne":"Napoli","nameTwo":"Juventus","1":"2.20","X":"3.15","2":"3.35"}],"Football. Italy. Serie B.":[{"result":"2:0(1:0)","nameOne":"Atalanta","nameTwo":"Grosseto","1":"1.40","X":"3.85","2":"8.40"}],"Football. Germany. 2 Bundesliga.":[{"result":"1:0(0:0)","nameOne":"Erzgebirge Aue","nameTwo":"Paderborn 07","1":"2.00","X":"3.30","2":"3.40"},{"result":"1:1(0:0)","nameOne":"Karlsruher","nameTwo":"Greuther Furth","1":"2.55","X":"3.20","2":"2.55"},{"result":"1:3(0:1)","nameOne":"1860 Munich","nameTwo":"Bochum","1":"2.35","X":"3.25","2":"2.75"},{"result":"2:0(1:0)","nameOne":"FC Augsburg","nameTwo":"Ingolstadt 04","1":"1.52","X":"3.80","2":"5.70"},{"result":"1:1(0:0)","nameOne":"DSC Arminia Bielefeld","nameTwo":"Frankfurt","1":"2.60","X":"3.20","2":"2.50"},{"result":"4:1(1:1)","nameOne":"MSV Duisburg","nameTwo":"Osnabruck","1":"1.55","X":"3.80","2":"5.30"},{"result":"1:3(1:1)","nameOne":"Rot-Weiss Oberhausen","nameTwo":"Hertha","1":"4.50","X":"3.40","2":"1.72"}],"Football. French Cup.":[{"result":"2:2(0:2), pass 2","nameOne":"Aurillac","nameTwo":"Nancy","1":"8.40","X":"4.50","2":"1.33"},{"result":"0:0(0:0), pass 2","nameOne":"Issy-les-Moulineaux","nameTwo":"Stade Brestois 29","1":"10.50","X":"5.50","2":"1.22"},{"result":"2:2(1:1), pass 1","nameOne":"US Boulogne-sur-Mer","nameTwo":"Amiens SC","1":"1.80","X":"3.20","2":"4.40"},{"result":"7:0(4:0), pass 1","nameOne":"Rennes","nameTwo":"AS Cannes","1":"1.35","X":"4.50","2":"7.80"},{"result":"3:1(2:0), pass 1","nameOne":"Evian TG","nameTwo":"Marseille","1":"4.35","X":"3.15","2":"1.85"}],"Football. Portugal. Liga Sagres.":[{"result":"0:1(0:1)","nameOne":"Rio Ave","nameTwo":"Olhanense","1":"2.15","X":"3.05","2":"3.20"},{"result":"0:0(0:0)","nameOne":"Nacional Madeira","nameTwo":"SC Beira-Mar","1":"1.85","X":"3.20","2":"4.00"},{"result":"0:0(0:0)","nameOne":"Academica Coimbra","nameTwo":"Pacos de Ferreira","1":"2.15","X":"3.00","2":"3.20"},{"result":"1:2(1:0)","nameOne":"Vitoria Guimaraes","nameTwo":"Naval de Maio","1":"1.50","X":"3.70","2":"6.10"},{"result":"0:3(0:1)","nameOne":"UD Leiria","nameTwo":"Benfica","1":"5.80","X":"3.40","2":"1.57"}],"Football. Portugal. Liga de Honra.":[{"result":"0:1(0:0)","nameOne":"Trofense","nameTwo":"Arouca","1":"1.90","X":"3.15","2":"3.75"},{"result":"3:3(2:1)","nameOne":"Freamunde","nameTwo":"Leixoes","1":"2.65","X":"3.00","2":"2.50"},{"result":"2:1(2:0)","nameOne":"Aves","nameTwo":"Santa Clara","1":"2.05","X":"3.10","2":"3.35"},{"result":"1:1(1:1)","nameOne":"Fatima","nameTwo":"Sporting Covilha","1":"2.05","X":"3.00","2":"3.45"},{"result":"1:1(0:0)","nameOne":"Varzim SC","nameTwo":"Moreirense","1":"1.90","X":"3.15","2":"3.75"}],"Football. Greece. Super League.":[{"result":"0:2(0:2)","nameOne":"Panionios","nameTwo":"Skoda Xanthi","1":"2.00","X":"2.90","2":"3.70"},{"result":"1:0(1:0)","nameOne":"Iraklis Thessaloniki","nameTwo":"PAE APS Atromitos Athens","1":"2.25","X":"2.90","2":"3.10"},{"result":"0:0(0:0)","nameOne":"Ergotelis","nameTwo":"Olimpiakos Volos","1":"2.20","X":"2.80","2":"3.30"},{"result":"1:0(1:0)","nameOne":"PAOK","nameTwo":"Asteras Tripolis FC","1":"1.45","X":"3.55","2":"7.00"},{"result":"1:3(1:2)","nameOne":"Panserraikos","nameTwo":"AEK Athens F.C.","1":"3.80","X":"2.95","2":"1.95"},{"result":"0:2(0:0)","nameOne":"Kerkyra","nameTwo":"Olympiakos Piraeus","1":"9.00","X":"3.80","2":"1.35"}],"Football. Scottish Cup.":[{"result":"0:4(0:1)","nameOne":"FC Dundee","nameTwo":"Motherwell","1":"2.70","X":"3.25","2":"2.25"},{"result":"cancelled","nameOne":"Hearts","nameTwo":"Saint Johnstone","1":"1.50","X":"3.70","2":"5.40"},{"result":"0:2(0:1)","nameOne":"Berwick Rangers FC","nameTwo":"Celtic","1":"20.60","X":"8.50","2":"1.04"}],"Football. Israel. Premier League.":[{"result":"1:3(1:1)","nameOne":"Maccabi Petah Tikva","nameTwo":"Maccabi Haifa","1":"3.20","X":"3.20","2":"2.05"}],"Football. Mexico. Primera Division.":[{"result":"1:1(0:1)","nameOne":"Puebla","nameTwo":"Guadalajara Chivas","1":"2.50","X":"3.10","2":"2.60"},{"result":"1:1(1:0)","nameOne":"Toluca","nameTwo":"Pumas UNAM","1":"1.90","X":"3.20","2":"3.70"},{"result":"0:2(0:1)","nameOne":"Club America","nameTwo":"Pachuca","1":"1.90","X":"3.20","2":"3.70"}]}